README.txt
setup.cfg
setup.py
jsonrpc2_base/__init__.py
jsonrpc2_base/client.py
jsonrpc2_base/header_factory.py
jsonrpc2_base/jsonrpc_base_exception.py
jsonrpc2_base/jsonrpc_exception.py
jsonrpc2_base/method_mapper.py
jsonrpc2_base/server.py
jsonrpc2_base.egg-info/PKG-INFO
jsonrpc2_base.egg-info/SOURCES.txt
jsonrpc2_base.egg-info/dependency_links.txt
jsonrpc2_base.egg-info/top_level.txt
jsonrpc2_base/endpoint/__init__.py
jsonrpc2_base/endpoint/endpoint_base.py
jsonrpc2_base/endpoint/router.py
jsonrpc2_base/plugins/__init__.py
jsonrpc2_base/plugins/client/__init__.py
jsonrpc2_base/plugins/client/client_plugin_base.py
jsonrpc2_base/plugins/client/debug_logger.py
jsonrpc2_base/plugins/client/signature_add.py
jsonrpc2_base/plugins/server/__init__.py
jsonrpc2_base/plugins/server/reflection_plugin.py
jsonrpc2_base/plugins/server/server_plugin_base.py
tests/__init__.py
tests/header_factory_test.py